polka/__init__.py
polka/analysis.py
polka/generate.py
polka/keyflow.py
polka/keyflow_multicast.py
polka/tools.py
polka_routing-0.2.2.dist-info/AUTHORS.rst
polka_routing-0.2.2.dist-info/LICENSE
polka_routing-0.2.2.dist-info/LICENSE.txt
polka_routing-0.2.2.dist-info/METADATA
polka_routing-0.2.2.dist-info/WHEEL
polka_routing-0.2.2.dist-info/top_level.txt
polka_routing-0.2.2.dist-info/RECORD
