Metadata-Version: 2.1
Name: polka-routing
Version: 0.2.2
Summary: PolKA - A Polynomial Scrict-Source Routing - Tools
Home-page: https://github.com/nerds-ufes/polka
Author: rafaelsilvag
Author-email: rafaelsg@gmail.com
License: mit
Project-URL: Documentation, https://nerds.inf.ufes.br/
Platform: any
Classifier: Development Status :: 4 - Beta
Classifier: Programming Language :: Python
Requires-Python: !=3.0.*,!=3.1.*,!=3.2.*,!=3.3.*,>=2.7
Requires-Dist: numpy (>=1.11.0)
Requires-Dist: sympy (>=1.5.0)
Requires-Dist: pandas (>=1.0.0)
Requires-Dist: networkx
Provides-Extra: testing
Requires-Dist: pytest ; extra == 'testing'
Requires-Dist: pytest-cov ; extra == 'testing'
